fullqualname.py
fullqualname-0.1.0.dist-info/DESCRIPTION.rst
fullqualname-0.1.0.dist-info/METADATA
fullqualname-0.1.0.dist-info/metadata.json
fullqualname-0.1.0.dist-info/RECORD
fullqualname-0.1.0.dist-info/top_level.txt
fullqualname-0.1.0.dist-info/WHEEL
