Metadata-Version: 2.0
Name: fullqualname
Version: 0.1.0
Summary: Fully qualified names for Python objects
Home-page: https://github.com/etgalloway/fullqualname
Author: Eric Galloway
Author-email: ericgalloway@gmail.com
License: UNKNOWN
Keywords: introspection
Platform: UNKNOWN
Classifier: License :: OSI Approved :: BSD License
Classifier: Operating System :: OS Independent
Classifier: Programming Language :: Python
Classifier: Programming Language :: Python :: 2
Classifier: Programming Language :: Python :: 3
Classifier: Programming Language :: Python :: 2.7
Classifier: Programming Language :: Python :: 3.3
Classifier: Programming Language :: Python :: 3.4
